expanse_cli/__init__.py
expanse_cli/__version__.py
expanse_cli/commands/__init__.py
expanse_cli/commands/new.py
expanse_cli/main.py
expanse_cli-0.3.0.dist-info/METADATA
expanse_cli-0.3.0.dist-info/WHEEL
expanse_cli-0.3.0.dist-info/entry_points.txt
expanse_cli-0.3.0.dist-info/RECORD
